intent/__init__.py
intent/intent.py
intent-0.0.4.dist-info/AUTHORS.rst
intent-0.0.4.dist-info/LICENSE
intent-0.0.4.dist-info/METADATA
intent-0.0.4.dist-info/WHEEL
intent-0.0.4.dist-info/top_level.txt
intent-0.0.4.dist-info/RECORD
